nouveau/__doc__
nouveau/__init__.py
nouveau/morris.csv
nouveau-0.0.5.dist-info/METADATA
nouveau-0.0.5.dist-info/WHEEL
nouveau-0.0.5.dist-info/top_level.txt
nouveau-0.0.5.dist-info/zip-safe
nouveau-0.0.5.dist-info/RECORD
