Metadata-Version: 2.1
Name: nouveau
Version: 0.0.5
Summary: public domain art nouveau image data
Home-page: https://github.com/dactylroot/nouveau
Download-URL: https://github.com/dactylroot/nouveau/archive/0.0.5.tar.gz
License: Unlicense
Keywords: art,data,dataset
Classifier: Development Status :: 5 - Production/Stable
Classifier: License :: OSI Approved :: The Unlicense (Unlicense)
Classifier: Topic :: Scientific/Engineering :: Artificial Intelligence
Requires-Python: >=3.5
Requires-Dist: pandas
Requires-Dist: numpy
Requires-Dist: pillow
Requires-Dist: scikit-learn
